[{"Year":"1960","Rural population (% of total population)":"82.076","Urban population (% of total)":"17.924"},{"Year":"1961","Rural population (% of total population)":"81.968","Urban population (% of total)":"18.032"},{"Year":"1962","Rural population (% of total population)":"81.782","Urban population (% of total)":"18.218"},{"Year":"1963","Rural population (% of total population)":"81.595","Urban population (% of total)":"18.405"},{"Year":"1964","Rural population (% of total population)":"81.405","Urban population (% of total)":"18.595"},{"Year":"1965","Rural population (% of total population)":"81.215","Urban population (% of total)":"18.785"},{"Year":"1966","Rural population (% of total population)":"81.023","Urban population (% of total)":"18.977"},{"Year":"1967","Rural population (% of total population)":"80.829","Urban population (% of total)":"19.171"},{"Year":"1968","Rural population (% of total population)":"80.634","Urban population (% of total)":"19.366"},{"Year":"1969","Rural population (% of total population)":"80.438","Urban population (% of total)":"19.562"},{"Year":"1970","Rural population (% of total population)":"80.24","Urban population (% of total)":"19.76"},{"Year":"1971","Rural population (% of total population)":"80.009","Urban population (% of total)":"19.991"},{"Year":"1972","Rural population (% of total population)":"79.679","Urban population (% of total)":"20.321"},{"Year":"1973","Rural population (% of total population)":"79.347","Urban population (% of total)":"20.653"},{"Year":"1974","Rural population (% of total population)":"79.009","Urban population (% of total)":"20.991"},{"Year":"1975","Rural population (% of total population)":"78.668","Urban population (% of total)":"21.332"},{"Year":"1976","Rural population (% of total population)":"78.323","Urban population (% of total)":"21.677"},{"Year":"1977","Rural population (% of total population)":"77.974","Urban population (% of total)":"22.026"},{"Year":"1978","Rural population (% of total population)":"77.621","Urban population (% of total)":"22.379"},{"Year":"1979","Rural population (% of total population)":"77.264","Urban population (% of total)":"22.736"},{"Year":"1980","Rural population (% of total population)":"76.902","Urban population (% of total)":"23.098"},{"Year":"1981","Rural population (% of total population)":"76.583","Urban population (% of total)":"23.417"},{"Year":"1982","Rural population (% of total population)":"76.353","Urban population (% of total)":"23.647"},{"Year":"1983","Rural population (% of total population)":"76.121","Urban population (% of total)":"23.879"},{"Year":"1984","Rural population (% of total population)":"75.887","Urban population (% of total)":"24.113"},{"Year":"1985","Rural population (% of total population)":"75.652","Urban population (% of total)":"24.348"},{"Year":"1986","Rural population (% of total population)":"75.415","Urban population (% of total)":"24.585"},{"Year":"1987","Rural population (% of total population)":"75.177","Urban population (% of total)":"24.823"},{"Year":"1988","Rural population (% of total population)":"74.937","Urban population (% of total)":"25.063"},{"Year":"1989","Rural population (% of total population)":"74.695","Urban population (% of total)":"25.305"},{"Year":"1990","Rural population (% of total population)":"74.453","Urban population (% of total)":"25.547"},{"Year":"1991","Rural population (% of total population)":"74.222","Urban population (% of total)":"25.778"},{"Year":"1992","Rural population (% of total population)":"74.016","Urban population (% of total)":"25.984"},{"Year":"1993","Rural population (% of total population)":"73.809","Urban population (% of total)":"26.191"},{"Year":"1994","Rural population (% of total population)":"73.601","Urban population (% of total)":"26.399"},{"Year":"1995","Rural population (% of total population)":"73.393","Urban population (% of total)":"26.607"},{"Year":"1996","Rural population (% of total population)":"73.183","Urban population (% of total)":"26.817"},{"Year":"1997","Rural population (% of total population)":"72.972","Urban population (% of total)":"27.028"},{"Year":"1998","Rural population (% of total population)":"72.76","Urban population (% of total)":"27.24"},{"Year":"1999","Rural population (% of total population)":"72.547","Urban population (% of total)":"27.453"},{"Year":"2000","Rural population (% of total population)":"72.333","Urban population (% of total)":"27.667"},{"Year":"2001","Rural population (% of total population)":"72.082","Urban population (% of total)":"27.918"},{"Year":"2002","Rural population (% of total population)":"71.756","Urban population (% of total)":"28.244"},{"Year":"2003","Rural population (% of total population)":"71.428","Urban population (% of total)":"28.572"},{"Year":"2004","Rural population (% of total population)":"71.097","Urban population (% of total)":"28.903"},{"Year":"2005","Rural population (% of total population)":"70.765","Urban population (% of total)":"29.235"},{"Year":"2006","Rural population (% of total population)":"70.431","Urban population (% of total)":"29.569"},{"Year":"2007","Rural population (% of total population)":"70.094","Urban population (% of total)":"29.906"},{"Year":"2008","Rural population (% of total population)":"69.754","Urban population (% of total)":"30.246"},{"Year":"2009","Rural population (% of total population)":"69.413","Urban population (% of total)":"30.587"},{"Year":"2010","Rural population (% of total population)":"69.07","Urban population (% of total)":"30.93"},{"Year":"2011","Rural population (% of total population)":"68.724","Urban population (% of total)":"31.276"},{"Year":"2012","Rural population (% of total population)":"68.369","Urban population (% of total)":"31.631"},{"Year":"2013","Rural population (% of total population)":"68.006","Urban population (% of total)":"31.994"},{"Year":"2014","Rural population (% of total population)":"67.634","Urban population (% of total)":"32.366"},{"Year":"2015","Rural population (% of total population)":"0","Urban population (% of total)":"0"}]